kraken_gstorage/kraken_gstorage.py
kraken_gstorage-0.0.1.dist-info/LICENSE.txt
kraken_gstorage-0.0.1.dist-info/METADATA
kraken_gstorage-0.0.1.dist-info/WHEEL
kraken_gstorage-0.0.1.dist-info/top_level.txt
kraken_gstorage-0.0.1.dist-info/RECORD
